{"{": 5, "Infobox": 2, "01-CODE": 2, "01-BEZEICHNUNG": 2, "Koronarthrombose": 1, "nachfolgenden": 1, "Myokardinfarkt": 1, "}": 3, "ist": 2, "Bildung": 1, "[": 15, "]": 3, "Koronargefäß|Herzkranzgefäß": 1, "Spezialfall": 1, "Thrombose": 1, "sie": 1, "Teil": 1, "Herzkrankheit": 1, "Gesundheitshinweis": 1, "Kategorie": 3, "Krankheitsbild": 2, "Kardiologie": 1, "Angiologie": 1, "AUSRICHTUNG": 1, "Neurologischer": 1, "Olfaktorische": 1, "Neglect": 3, "bezeichnet": 1, "vorkommende": 1, "Form": 1, "betroffene": 1, "Patient": 1, "kann": 1, "Nasenloch": 1, "betroffenen": 1, "Körperseite": 1, "Gerüche": 1, "wahrnehmen": 1, "Andere": 1, "Sonderformen": 1, "Neglects": 1, "*": 1, "Visueller": 1, "Sehen": 1, "Somatosensibler": 1, "Tastsinn": 1, "Auditorischer": 1, "Hören": 1, "Neuropsychologisches": 1, "Syndrom": 1}